[
  {
    "ContainingType": "PostAPI.Controllers.PostController",
    "Method": "GetAll",
    "RelativePath": "api/Post/GetAll",
    "HttpMethod": "GET",
    "IsController": true,
    "Order": 0,
    "Parameters": [],
    "ReturnTypes": [
      {
        "Type": "System.Collections.Generic.List\u00601[[Domain.PostsEntity, Domain, Version=1.0.0.0, Culture=neutral, PublicKeyToken=null]]",
        "MediaTypes": [
          "text/plain",
          "application/json",
          "text/json"
        ],
        "StatusCode": 200
      }
    ]
  },
  {
    "ContainingType": "PostAPI.Controllers.PostController",
    "Method": "InsertPost",
    "RelativePath": "api/Post/InsertPost",
    "HttpMethod": "POST",
    "IsController": true,
    "Order": 0,
    "Parameters": [
      {
        "Name": "payload",
        "Type": "DTO.PostDTO",
        "IsRequired": true
      }
    ],
    "ReturnTypes": [
      {
        "Type": "System.Boolean",
        "MediaTypes": [
          "text/plain",
          "application/json",
          "text/json"
        ],
        "StatusCode": 200
      }
    ]
  },
  {
    "ContainingType": "Program\u002B\u003C\u003Ec",
    "Method": "\u003C\u003CMain\u003E$\u003Eb__0_0",
    "RelativePath": "health",
    "HttpMethod": "GET",
    "IsController": false,
    "Order": 0,
    "Parameters": [],
    "ReturnTypes": [
      {
        "Type": "System.Void",
        "MediaTypes": [],
        "StatusCode": 200
      }
    ]
  },
  {
    "ContainingType": "Program\u002B\u003C\u003Ec",
    "Method": "\u003C\u003CMain\u003E$\u003Eb__0_0",
    "RelativePath": "health",
    "HttpMethod": "HEAD",
    "IsController": false,
    "Order": 0,
    "Parameters": [],
    "ReturnTypes": [
      {
        "Type": "System.Void",
        "MediaTypes": [],
        "StatusCode": 200
      }
    ]
  }
]